LICENSE
README.md
pyproject.toml
src/xingshu_cta_jymokuai.egg-info/PKG-INFO
src/xingshu_cta_jymokuai.egg-info/SOURCES.txt
src/xingshu_cta_jymokuai.egg-info/dependency_links.txt
src/xingshu_cta_jymokuai.egg-info/requires.txt
src/xingshu_cta_jymokuai.egg-info/top_level.txt
src/xingshu_ctastrategy/__init__.py
src/xingshu_ctastrategy/模块_CTA引擎.py
src/xingshu_ctastrategy/模块_基础.py
src/xingshu_ctastrategy/模块_模板.py
src/xingshu_ctastrategy/包_国际化/__init__.py
src/xingshu_ctastrategy/策略文件夹/策略_K线合成教程_2.py
src/xingshu_ctastrategy/策略文件夹/策略_基础教程_1.py
src/xingshu_ctastrategy/策略文件夹/策略_技术指标合成教程_3.py