Metadata-Version: 2.4
Name: xingshu_cta_jymokuai
Version: 1.0.1
Summary: 专为中文母语开发者打造的量化交易研发框架。
Author-email: bhzy <2024305928@qq.com>
License-Expression: MIT
Project-URL: Homepage, https://github.com/bhzyxyqy/xingshu
Project-URL: Issues, https://github.com/bhzyxyqy/xingshu/issues
Classifier: Programming Language :: Python :: 3
Classifier: Operating System :: OS Independent
Requires-Python: >=3.8
License-File: LICENSE
Requires-Dist: importlib_metadata>=8.6.1
Dynamic: license-file
